mycalc/calculator.py
mycalc2023_ossevo-0.0.1.dist-info/METADATA
mycalc2023_ossevo-0.0.1.dist-info/WHEEL
mycalc2023_ossevo-0.0.1.dist-info/top_level.txt
mycalc2023_ossevo-0.0.1.dist-info/RECORD
