Metadata-Version: 2.1
Name: mycalc2023-ossevo
Version: 0.0.1
Summary: nice calculator
Author: immm
Classifier: Programming Language :: Python :: 3
